{
  "id": "wooden_bow",
  "displayName": "Wooden Bow",
  "description": "A flexible ranged weapon that fires standard arrow ammunition.",
  "rarity": "Common",
  "value": 32,
  "category": "Weapon",
  "sortPriority": 40,
  "type": "WeaponRanged",
  "texture": "items/wooden_bow",
  "maxStack": 1,
  "useTime": 0.45,
  "damage": 4,
  "knockback": 1.0,
  "actions": [
    {
      "kind": "Shoot",
      "projectile": "wooden_arrow",
      "ammo": "wooden_arrow",
      "ammoCost": 1,
      "projectileSpeedMultiplier": 1.0
    }
  ],
  "tags": ["weapon", "ranged", "starter"]
}
